odoo/addons/purchase_partner_incoterm/README.rst
odoo/addons/purchase_partner_incoterm/__init__.py
odoo/addons/purchase_partner_incoterm/__manifest__.py
odoo/addons/purchase_partner_incoterm/i18n/purchase_partner_incoterm.pot
odoo/addons/purchase_partner_incoterm/models/__init__.py
odoo/addons/purchase_partner_incoterm/models/purchase_order.py
odoo/addons/purchase_partner_incoterm/models/res_partner.py
odoo/addons/purchase_partner_incoterm/readme/CONTRIBUTORS.rst
odoo/addons/purchase_partner_incoterm/readme/CREDITS.rst
odoo/addons/purchase_partner_incoterm/readme/DESCRIPTION.rst
odoo/addons/purchase_partner_incoterm/static/description/icon.png
odoo/addons/purchase_partner_incoterm/static/description/index.html
odoo/addons/purchase_partner_incoterm/views/partner_view.xml
odoo/addons/purchase_partner_incoterm/views/purchase_view.xml
odoo14_addon_purchase_partner_incoterm-14.0.2.0.0.dist-info/METADATA
odoo14_addon_purchase_partner_incoterm-14.0.2.0.0.dist-info/WHEEL
odoo14_addon_purchase_partner_incoterm-14.0.2.0.0.dist-info/top_level.txt
odoo14_addon_purchase_partner_incoterm-14.0.2.0.0.dist-info/RECORD
